flowi/__init__.py
flowi/__main__.py
flowi/global_state.py
flowi/settings.py
flowi/components/__init__.py
flowi/components/component_base.py
flowi/components/data_preparation/__init__.py
flowi/components/data_preparation/_sklearn.py
flowi/components/label/__init__.py
flowi/components/label/_label.py
flowi/components/label/_transformers.py
flowi/components/load/__init__.py
flowi/components/load/_load_local.py
flowi/components/load/_load_s3.py
flowi/components/metrics/__init__.py
flowi/components/metrics/_classification.py
flowi/components/metrics/_regression.py
flowi/components/model_selection/__init__.py
flowi/components/model_selection/_model_selection.py
flowi/components/models/__init__.py
flowi/components/models/_classification.py
flowi/components/models/_regression.py
flowi/components/models/_wrappers.py
flowi/components/monitoring/__init__.py
flowi/components/monitoring/_drift.py
flowi/components/preprocessing/__init__.py
flowi/components/preprocessing/_preprocessing_dataframe.py
flowi/components/preprocessing/preprocessing_audio.py
flowi/components/preprocessing/preprocessing_base.py
flowi/components/preprocessing/preprocessing_labels.py
flowi/components/preprocessing/preprocessing_string.py
flowi/components/preprocessing/preprocessing_utils.py
flowi/components/preprocessing/transformers.py
flowi/components/save/__init__.py
flowi/components/save/_save_local.py
flowi/components/save/_save_s3.py
flowi/connections/__init__.py
flowi/connections/aws/__init__.py
flowi/connections/aws/s3.py
flowi/experiment_tracking/__init__.py
flowi/experiment_tracking/_base.py
flowi/experiment_tracking/_mlflow.py
flowi/experiment_tracking/experiment_tracking.py
flowi/experiment_tracking/utils.py
flowi/experiment_tracking/flavors/__init__.py
flowi/experiment_tracking/flavors/pytorch_flavor.py
flowi/experiment_tracking/flavors/sklearn_flavor.py
flowi/flow_chart/__init__.py
flowi/flow_chart/flow_chart.py
flowi/flow_chart/node.py
flowi/flow_chart/topology.py
flowi-0.5.13.dist-info/WHEEL
flowi-0.5.13.dist-info/METADATA
flowi-0.5.13.dist-info/RECORD
